Metadata-Version: 1.0
Name: marcin-awesome-project
Version: 0.0.1
Summary: Some awesome project
Home-page: UNKNOWN
Author: Marcin
Author-email: marcin.sopot@gmail.com
License: UNKNOWN
Platform: UNKNOWN
